python_thingsdb-1.3.2.dist-info/licenses/LICENSE
thingsdb/__init__.py
thingsdb/exceptions.py
thingsdb/version.py
thingsdb/client/__init__.py
thingsdb/client/baseprotocol.py
thingsdb/client/buildin.py
thingsdb/client/client.py
thingsdb/client/package.py
thingsdb/client/protocol.py
thingsdb/client/wsprotocol.py
thingsdb/misc/__init__.py
thingsdb/misc/lock.py
thingsdb/room/__init__.py
thingsdb/room/event.py
thingsdb/room/room.py
thingsdb/room/roombase.py
thingsdb/util/__init__.py
thingsdb/util/access.py
thingsdb/util/cleancode.py
thingsdb/util/cnscope.py
thingsdb/util/id.py
thingsdb/util/is_name.py
python_thingsdb-1.3.2.dist-info/METADATA
python_thingsdb-1.3.2.dist-info/WHEEL
python_thingsdb-1.3.2.dist-info/top_level.txt
python_thingsdb-1.3.2.dist-info/RECORD
