Metadata-Version: 2.4
Name: python-thingsdb
Version: 1.3.2
Summary: ThingsDB Connector
Home-page: https://github.com/thingsdb/python-thingsdb
Author: Jeroen van der Heijden
Author-email: jeroen@cesbit.com
License: MIT
Keywords: database connector
Classifier: Development Status :: 4 - Beta
Classifier: Intended Audience :: Developers
Classifier: Topic :: Software Development :: Build Tools
Classifier: Programming Language :: Python :: 3.10
Classifier: Programming Language :: Python :: 3.11
Classifier: Programming Language :: Python :: 3.12
Classifier: Programming Language :: Python :: 3.13
License-File: LICENSE
Requires-Dist: msgpack
Dynamic: author
Dynamic: author-email
Dynamic: classifier
Dynamic: description
Dynamic: description-content-type
Dynamic: home-page
Dynamic: keywords
Dynamic: license
Dynamic: license-file
Dynamic: requires-dist
Dynamic: summary
